nlp_jp_gears/__init__.py
nlp_jp_gears/composer.py
nlp_jp_gears/remover.py
nlp_jp_gears/utils.py
nlp_jp_gears/zenhan.py
nlp_jp_gears-0.1.1.dist-info/WHEEL
nlp_jp_gears-0.1.1.dist-info/METADATA
nlp_jp_gears-0.1.1.dist-info/RECORD
